Workbook

Sheet Read me
A1: Golden-set adjudication
A2: For the person resolving disagreements between the two annotators (SPEC §12.4: "two annotators with disagreements resolved").
A4: 1. Open each annotator's returned file, select their whole Labels tab (Ctrl+A), copy, and paste into cell A1 of 'Annotator A' / 'Annotator B' here.
A5: 2. The Compare tab lines up A, B and the original draft label for every field. Rows where A and B differ are shaded.
A6: 3. For each shaded row, decide and type the final label in the yellow 'Agreed' column. Where A and B agree, 'Agreed' may be left blank — the agreed value is used.
A7: 4. Use cases are free text, so they are never auto-compared: read both and write the agreed list.
A8: 5. Send this file back. The agreed labels replace the draft groundTruth blocks in tests/evals/cases.ts.
A10: The 'Draft' column is the single-author first pass already in the code. It is shown only here, never to the annotators, so it could not bias their reads.
A11: The Key tab maps each L-ID to its case in the code and its SPEC group. Annotators never saw the groups.

Sheet Compare
A1: ID | B1: SPEC group | C1: Field | D1: Draft (code today) | E1: Annotator A | F1: Annotator B | G1: A vs B | H1: Agreed | I1: Final label | K1: Rows where A and B differ: | L1: =COUNTIF(G2:G801,"DIFFER")
A2: L01 | B2: near-duplicate | C2: Use cases | D2: single status view showing current approver and elapsed time | E2: =IFERROR(INDEX('Annotator A'!$C$5:$C$44,MATCH($A2,'Annotator A'!$A$5:$A$44,0))&"","") | F2: =IFERROR(INDEX('Annotator B'!$C$5:$C$44,MATCH($A2,'Annotator B'!$A$5:$A$44,0))&"","") | G2: read both | I2: =IF(H2<>"",H2,"") | K2: Differing rows still without an agreed label: | L2: =COUNTIFS(G2:G801,"DIFFER",H2:H801,"")
A3: L01 | B3: near-duplicate | C3: Value — Business impact | E3: =IFERROR(INDEX('Annotator A'!$D$5:$D$44,MATCH($A3,'Annotator A'!$A$5:$A$44,0))&"","") | F3: =IFERROR(INDEX('Annotator B'!$D$5:$D$44,MATCH($A3,'Annotator B'!$A$5:$A$44,0))&"","") | G3: =IF(AND(E3="",F3=""),"",IF(E3=F3,"agree","DIFFER")) | I3: =IF(H3<>"",H3,IF(G3="agree",E3,""))
A4: L01 | B4: near-duplicate | C4: Value — Productivity | E4: =IFERROR(INDEX('Annotator A'!$E$5:$E$44,MATCH($A4,'Annotator A'!$A$5:$A$44,0))&"","") | F4: =IFERROR(INDEX('Annotator B'!$E$5:$E$44,MATCH($A4,'Annotator B'!$A$5:$A$44,0))&"","") | G4: =IF(AND(E4="",F4=""),"",IF(E4=F4,"agree","DIFFER")) | I4: =IF(H4<>"",H4,IF(G4="agree",E4,""))
A5: L01 | B5: near-duplicate | C5: Value — Cost reduction | E5: =IFERROR(INDEX('Annotator A'!$F$5:$F$44,MATCH($A5,'Annotator A'!$A$5:$A$44,0))&"","") | F5: =IFERROR(INDEX('Annotator B'!$F$5:$F$44,MATCH($A5,'Annotator B'!$A$5:$A$44,0))&"","") | G5: =IF(AND(E5="",F5=""),"",IF(E5=F5,"agree","DIFFER")) | I5: =IF(H5<>"",H5,IF(G5="agree",E5,""))
A6: L01 | B6: near-duplicate | C6: Value — Revenue | E6: =IFERROR(INDEX('Annotator A'!$G$5:$G$44,MATCH($A6,'Annotator A'!$A$5:$A$44,0))&"","") | F6: =IFERROR(INDEX('Annotator B'!$G$5:$G$44,MATCH($A6,'Annotator B'!$A$5:$A$44,0))&"","") | G6: =IF(AND(E6="",F6=""),"",IF(E6=F6,"agree","DIFFER")) | I6: =IF(H6<>"",H6,IF(G6="agree",E6,""))
A7: L01 | B7: near-duplicate | C7: Value — Employee experience | E7: =IFERROR(INDEX('Annotator A'!$H$5:$H$44,MATCH($A7,'Annotator A'!$A$5:$A$44,0))&"","") | F7: =IFERROR(INDEX('Annotator B'!$H$5:$H$44,MATCH($A7,'Annotator B'!$A$5:$A$44,0))&"","") | G7: =IF(AND(E7="",F7=""),"",IF(E7=F7,"agree","DIFFER")) | I7: =IF(H7<>"",H7,IF(G7="agree",E7,""))
A8: L01 | B8: near-duplicate | C8: Value — Customer impact | E8: =IFERROR(INDEX('Annotator A'!$I$5:$I$44,MATCH($A8,'Annotator A'!$A$5:$A$44,0))&"","") | F8: =IFERROR(INDEX('Annotator B'!$I$5:$I$44,MATCH($A8,'Annotator B'!$A$5:$A$44,0))&"","") | G8: =IF(AND(E8="",F8=""),"",IF(E8=F8,"agree","DIFFER")) | I8: =IF(H8<>"",H8,IF(G8="agree",E8,""))
A9: L01 | B9: near-duplicate | C9: Value — Operational | D9: Moderate | E9: =IFERROR(INDEX('Annotator A'!$J$5:$J$44,MATCH($A9,'Annotator A'!$A$5:$A$44,0))&"","") | F9: =IFERROR(INDEX('Annotator B'!$J$5:$J$44,MATCH($A9,'Annotator B'!$A$5:$A$44,0))&"","") | G9: =IF(AND(E9="",F9=""),"",IF(E9=F9,"agree","DIFFER")) | I9: =IF(H9<>"",H9,IF(G9="agree",E9,""))
A10: L01 | B10: near-duplicate | C10: Value — Problem severity | E10: =IFERROR(INDEX('Annotator A'!$K$5:$K$44,MATCH($A10,'Annotator A'!$A$5:$A$44,0))&"","") | F10: =IFERROR(INDEX('Annotator B'!$K$5:$K$44,MATCH($A10,'Annotator B'!$A$5:$A$44,0))&"","") | G10: =IF(AND(E10="",F10=""),"",IF(E10=F10,"agree","DIFFER")) | I10: =IF(H10<>"",H10,IF(G10="agree",E10,""))
A11: L01 | B11: near-duplicate | C11: Value — Problem frequency | D11: High | E11: =IFERROR(INDEX('Annotator A'!$L$5:$L$44,MATCH($A11,'Annotator A'!$A$5:$A$44,0))&"","") | F11: =IFERROR(INDEX('Annotator B'!$L$5:$L$44,MATCH($A11,'Annotator B'!$A$5:$A$44,0))&"","") | G11: =IF(AND(E11="",F11=""),"",IF(E11=F11,"agree","DIFFER")) | I11: =IF(H11<>"",H11,IF(G11="agree",E11,""))
A12: L01 | B12: near-duplicate | C12: Feasibility status | D12: FEASIBLE_WITH_CONDITIONS | E12: =IFERROR(INDEX('Annotator A'!$M$5:$M$44,MATCH($A12,'Annotator A'!$A$5:$A$44,0))&"","") | F12: =IFERROR(INDEX('Annotator B'!$M$5:$M$44,MATCH($A12,'Annotator B'!$A$5:$A$44,0))&"","") | G12: =IF(AND(E12="",F12=""),"",IF(E12=F12,"agree","DIFFER")) | I12: =IF(H12<>"",H12,IF(G12="agree",E12,""))
A13: L01 | B13: near-duplicate | C13: Risk — Technical | E13: =IFERROR(INDEX('Annotator A'!$N$5:$N$44,MATCH($A13,'Annotator A'!$A$5:$A$44,0))&"","") | F13: =IFERROR(INDEX('Annotator B'!$N$5:$N$44,MATCH($A13,'Annotator B'!$A$5:$A$44,0))&"","") | G13: =IF(AND(E13="",F13=""),"",IF(E13=F13,"agree","DIFFER")) | I13: =IF(H13<>"",H13,IF(G13="agree",E13,""))
A14: L01 | B14: near-duplicate | C14: Risk — Security | E14: =IFERROR(INDEX('Annotator A'!$O$5:$O$44,MATCH($A14,'Annotator A'!$A$5:$A$44,0))&"","") | F14: =IFERROR(INDEX('Annotator B'!$O$5:$O$44,MATCH($A14,'Annotator B'!$A$5:$A$44,0))&"","") | G14: =IF(AND(E14="",F14=""),"",IF(E14=F14,"agree","DIFFER")) | I14: =IF(H14<>"",H14,IF(G14="agree",E14,""))
A15: L01 | B15: near-duplicate | C15: Risk — Privacy | E15: =IFERROR(INDEX('Annotator A'!$P$5:$P$44,MATCH($A15,'Annotator A'!$A$5:$A$44,0))&"","") | F15: =IFERROR(INDEX('Annotator B'!$P$5:$P$44,MATCH($A15,'Annotator B'!$A$5:$A$44,0))&"","") | G15: =IF(AND(E15="",F15=""),"",IF(E15=F15,"agree","DIFFER")) | I15: =IF(H15<>"",H15,IF(G15="agree",E15,""))
A16: L01 | B16: near-duplicate | C16: Risk — Compliance | E16: =IFERROR(INDEX('Annotator A'!$Q$5:$Q$44,MATCH($A16,'Annotator A'!$A$5:$A$44,0))&"","") | F16: =IFERROR(INDEX('Annotator B'!$Q$5:$Q$44,MATCH($A16,'Annotator B'!$A$5:$A$44,0))&"","") | G16: =IF(AND(E16="",F16=""),"",IF(E16=F16,"agree","DIFFER")) | I16: =IF(H16<>"",H16,IF(G16="agree",E16,""))
A17: L01 | B17: near-duplicate | C17: Risk — Financial | E17: =IFERROR(INDEX('Annotator A'!$R$5:$R$44,MATCH($A17,'Annotator A'!$A$5:$A$44,0))&"","") | F17: =IFERROR(INDEX('Annotator B'!$R$5:$R$44,MATCH($A17,'Annotator B'!$A$5:$A$44,0))&"","") | G17: =IF(AND(E17="",F17=""),"",IF(E17=F17,"agree","DIFFER")) | I17: =IF(H17<>"",H17,IF(G17="agree",E17,""))
A18: L01 | B18: near-duplicate | C18: Risk — Operational | E18: =IFERROR(INDEX('Annotator A'!$S$5:$S$44,MATCH($A18,'Annotator A'!$A$5:$A$44,0))&"","") | F18: =IFERROR(INDEX('Annotator B'!$S$5:$S$44,MATCH($A18,'Annotator B'!$A$5:$A$44,0))&"","") | G18: =IF(AND(E18="",F18=""),"",IF(E18=F18,"agree","DIFFER")) | I18: =IF(H18<>"",H18,IF(G18="agree",E18,""))
A19: L01 | B19: near-duplicate | C19: Risk — Adoption | E19: =IFERROR(INDEX('Annotator A'!$T$5:$T$44,MATCH($A19,'Annotator A'!$A$5:$A$44,0))&"","") | F19: =IFERROR(INDEX('Annotator B'!$T$5:$T$44,MATCH($A19,'Annotator B'!$A$5:$A$44,0))&"","") | G19: =IF(AND(E19="",F19=""),"",IF(E19=F19,"agree","DIFFER")) | I19: =IF(H19<>"",H19,IF(G19="agree",E19,""))
A20: L01 | B20: near-duplicate | C20: Risk — Data | E20: =IFERROR(INDEX('Annotator A'!$U$5:$U$44,MATCH($A20,'Annotator A'!$A$5:$A$44,0))&"","") | F20: =IFERROR(INDEX('Annotator B'!$U$5:$U$44,MATCH($A20,'Annotator B'!$A$5:$A$44,0))&"","") | G20: =IF(AND(E20="",F20=""),"",IF(E20=F20,"agree","DIFFER")) | I20: =IF(H20<>"",H20,IF(G20="agree",E20,""))
A21: L01 | B21: near-duplicate | C21: Risk — Vendor | E21: =IFERROR(INDEX('Annotator A'!$V$5:$V$44,MATCH($A21,'Annotator A'!$A$5:$A$44,0))&"","") | F21: =IFERROR(INDEX('Annotator B'!$V$5:$V$44,MATCH($A21,'Annotator B'!$A$5:$A$44,0))&"","") | G21: =IF(AND(E21="",F21=""),"",IF(E21=F21,"agree","DIFFER")) | I21: =IF(H21<>"",H21,IF(G21="agree",E21,""))
A22: L02 | B22: infeasible | C22: Use cases | E22: =IFERROR(INDEX('Annotator A'!$C$5:$C$44,MATCH($A22,'Annotator A'!$A$5:$A$44,0))&"","") | F22: =IFERROR(INDEX('Annotator B'!$C$5:$C$44,MATCH($A22,'Annotator B'!$A$5:$A$44,0))&"","") | G22: read both | I22: =IF(H22<>"",H22,"")
A23: L02 | B23: infeasible | C23: Value — Business impact | E23: =IFERROR(INDEX('Annotator A'!$D$5:$D$44,MATCH($A23,'Annotator A'!$A$5:$A$44,0))&"","") | F23: =IFERROR(INDEX('Annotator B'!$D$5:$D$44,MATCH($A23,'Annotator B'!$A$5:$A$44,0))&"","") | G23: =IF(AND(E23="",F23=""),"",IF(E23=F23,"agree","DIFFER")) | I23: =IF(H23<>"",H23,IF(G23="agree",E23,""))
A24: L02 | B24: infeasible | C24: Value — Productivity | E24: =IFERROR(INDEX('Annotator A'!$E$5:$E$44,MATCH($A24,'Annotator A'!$A$5:$A$44,0))&"","") | F24: =IFERROR(INDEX('Annotator B'!$E$5:$E$44,MATCH($A24,'Annotator B'!$A$5:$A$44,0))&"","") | G24: =IF(AND(E24="",F24=""),"",IF(E24=F24,"agree","DIFFER")) | I24: =IF(H24<>"",H24,IF(G24="agree",E24,""))
A25: L02 | B25: infeasible | C25: Value — Cost reduction | E25: =IFERROR(INDEX('Annotator A'!$F$5:$F$44,MATCH($A25,'Annotator A'!$A$5:$A$44,0))&"","") | F25: =IFERROR(INDEX('Annotator B'!$F$5:$F$44,MATCH($A25,'Annotator B'!$A$5:$A$44,0))&"","") | G25: =IF(AND(E25="",F25=""),"",IF(E25=F25,"agree","DIFFER")) | I25: =IF(H25<>"",H25,IF(G25="agree",E25,""))
A26: L02 | B26: infeasible | C26: Value — Revenue | E26: =IFERROR(INDEX('Annotator A'!$G$5:$G$44,MATCH($A26,'Annotator A'!$A$5:$A$44,0))&"","") | F26: =IFERROR(INDEX('Annotator B'!$G$5:$G$44,MATCH($A26,'Annotator B'!$A$5:$A$44,0))&"","") | G26: =IF(AND(E26="",F26=""),"",IF(E26=F26,"agree","DIFFER")) | I26: =IF(H26<>"",H26,IF(G26="agree",E26,""))
A27: L02 | B27: infeasible | C27: Value — Employee experience | E27: =IFERROR(INDEX('Annotator A'!$H$5:$H$44,MATCH($A27,'Annotator A'!$A$5:$A$44,0))&"","") | F27: =IFERROR(INDEX('Annotator B'!$H$5:$H$44,MATCH($A27,'Annotator B'!$A$5:$A$44,0))&"","") | G27: =IF(AND(E27="",F27=""),"",IF(E27=F27,"agree","DIFFER")) | I27: =IF(H27<>"",H27,IF(G27="agree",E27,""))
A28: L02 | B28: infeasible | C28: Value — Customer impact | E28: =IFERROR(INDEX('Annotator A'!$I$5:$I$44,MATCH($A28,'Annotator A'!$A$5:$A$44,0))&"","") | F28: =IFERROR(INDEX('Annotator B'!$I$5:$I$44,MATCH($A28,'Annotator B'!$A$5:$A$44,0))&"","") | G28: =IF(AND(E28="",F28=""),"",IF(E28=F28,"agree","DIFFER")) | I28: =IF(H28<>"",H28,IF(G28="agree",E28,""))
A29: L02 | B29: infeasible | C29: Value — Operational | E29: =IFERROR(INDEX('Annotator A'!$J$5:$J$44,MATCH($A29,'Annotator A'!$A$5:$A$44,0))&"","") | F29: =IFERROR(INDEX('Annotator B'!$J$5:$J$44,MATCH($A29,'Annotator B'!$A$5:$A$44,0))&"","") | G29: =IF(AND(E29="",F29=""),"",IF(E29=F29,"agree","DIFFER")) | I29: =IF(H29<>"",H29,IF(G29="agree",E29,""))
A30: L02 | B30: infeasible | C30: Value — Problem severity | E30: =IFERROR(INDEX('Annotator A'!$K$5:$K$44,MATCH($A30,'Annotator A'!$A$5:$A$44,0))&"","") | F30: =IFERROR(INDEX('Annotator B'!$K$5:$K$44,MATCH($A30,'Annotator B'!$A$5:$A$44,0))&"","") | G30: =IF(AND(E30="",F30=""),"",IF(E30=F30,"agree","DIFFER")) | I30: =IF(H30<>"",H30,IF(G30="agree",E30,""))
A31: L02 | B31: infeasible | C31: Value — Problem frequency | E31: =IFERROR(INDEX('Annotator A'!$L$5:$L$44,MATCH($A31,'Annotator A'!$A$5:$A$44,0))&"","") | F31: =IFERROR(INDEX('Annotator B'!$L$5:$L$44,MATCH($A31,'Annotator B'!$A$5:$A$44,0))&"","") | G31: =IF(AND(E31="",F31=""),"",IF(E31=F31,"agree","DIFFER")) | I31: =IF(H31<>"",H31,IF(G31="agree",E31,""))
A32: L02 | B32: infeasible | C32: Feasibility status | D32: NOT_CURRENTLY_FEASIBLE | E32: =IFERROR(INDEX('Annotator A'!$M$5:$M$44,MATCH($A32,'Annotator A'!$A$5:$A$44,0))&"","") | F32: =IFERROR(INDEX('Annotator B'!$M$5:$M$44,MATCH($A32,'Annotator B'!$A$5:$A$44,0))&"","") | G32: =IF(AND(E32="",F32=""),"",IF(E32=F32,"agree","DIFFER")) | I32: =IF(H32<>"",H32,IF(G32="agree",E32,""))
A33: L02 | B33: infeasible | C33: Risk — Technical | E33: =IFERROR(INDEX('Annotator A'!$N$5:$N$44,MATCH($A33,'Annotator A'!$A$5:$A$44,0))&"","") | F33: =IFERROR(INDEX('Annotator B'!$N$5:$N$44,MATCH($A33,'Annotator B'!$A$5:$A$44,0))&"","") | G33: =IF(AND(E33="",F33=""),"",IF(E33=F33,"agree","DIFFER")) | I33: =IF(H33<>"",H33,IF(G33="agree",E33,""))
A34: L02 | B34: infeasible | C34: Risk — Security | E34: =IFERROR(INDEX('Annotator A'!$O$5:$O$44,MATCH($A34,'Annotator A'!$A$5:$A$44,0))&"","") | F34: =IFERROR(INDEX('Annotator B'!$O$5:$O$44,MATCH($A34,'Annotator B'!$A$5:$A$44,0))&"","") | G34: =IF(AND(E34="",F34=""),"",IF(E34=F34,"agree","DIFFER")) | I34: =IF(H34<>"",H34,IF(G34="agree",E34,""))
A35: L02 | B35: infeasible | C35: Risk — Privacy | E35: =IFERROR(INDEX('Annotator A'!$P$5:$P$44,MATCH($A35,'Annotator A'!$A$5:$A$44,0))&"","") | F35: =IFERROR(INDEX('Annotator B'!$P$5:$P$44,MATCH($A35,'Annotator B'!$A$5:$A$44,0))&"","") | G35: =IF(AND(E35="",F35=""),"",IF(E35=F35,"agree","DIFFER")) | I35: =IF(H35<>"",H35,IF(G35="agree",E35,""))
A36: L02 | B36: infeasible | C36: Risk — Compliance | D36: Yes | E36: =IFERROR(INDEX('Annotator A'!$Q$5:$Q$44,MATCH($A36,'Annotator A'!$A$5:$A$44,0))&"","") | F36: =IFERROR(INDEX('Annotator B'!$Q$5:$Q$44,MATCH($A36,'Annotator B'!$A$5:$A$44,0))&"","") | G36: =IF(AND(E36="",F36=""),"",IF(E36=F36,"agree","DIFFER")) | I36: =IF(H36<>"",H36,IF(G36="agree",E36,""))
A37: L02 | B37: infeasible | C37: Risk — Financial | D37: Yes | E37: =IFERROR(INDEX('Annotator A'!$R$5:$R$44,MATCH($A37,'Annotator A'!$A$5:$A$44,0))&"","") | F37: =IFERROR(INDEX('Annotator B'!$R$5:$R$44,MATCH($A37,'Annotator B'!$A$5:$A$44,0))&"","") | G37: =IF(AND(E37="",F37=""),"",IF(E37=F37,"agree","DIFFER")) | I37: =IF(H37<>"",H37,IF(G37="agree",E37,""))
A38: L02 | B38: infeasible | C38: Risk — Operational | E38: =IFERROR(INDEX('Annotator A'!$S$5:$S$44,MATCH($A38,'Annotator A'!$A$5:$A$44,0))&"","") | F38: =IFERROR(INDEX('Annotator B'!$S$5:$S$44,MATCH($A38,'Annotator B'!$A$5:$A$44,0))&"","") | G38: =IF(AND(E38="",F38=""),"",IF(E38=F38,"agree","DIFFER")) | I38: =IF(H38<>"",H38,IF(G38="agree",E38,""))
A39: L02 | B39: infeasible | C39: Risk — Adoption | E39: =IFERROR(INDEX('Annotator A'!$T$5:$T$44,MATCH($A39,'Annotator A'!$A$5:$A$44,0))&"","") | F39: =IFERROR(INDEX('Annotator B'!$T$5:$T$44,MATCH($A39,'Annotator B'!$A$5:$A$44,0))&"","") | G39: =IF(AND(E39="",F39=""),"",IF(E39=F39,"agree","DIFFER")) | I39: =IF(H39<>"",H39,IF(G39="agree",E39,""))
A40: L02 | B40: infeasible | C40: Risk — Data | E40: =IFERROR(INDEX('Annotator A'!$U$5:$U$44,MATCH($A40,'Annotator A'!$A$5:$A$44,0))&"","") | F40: =IFERROR(INDEX('Annotator B'!$U$5:$U$44,MATCH($A40,'Annotator B'!$A$5:$A$44,0))&"","") | G40: =IF(AND(E40="",F40=""),"",IF(E40=F40,"agree","DIFFER")) | I40: =IF(H40<>"",H40,IF(G40="agree",E40,""))
A41: L02 | B41: infeasible | C41: Risk — Vendor | E41: =IFERROR(INDEX('Annotator A'!$V$5:$V$44,MATCH($A41,'Annotator A'!$A$5:$A$44,0))&"","") | F41: =IFERROR(INDEX('Annotator B'!$V$5:$V$44,MATCH($A41,'Annotator B'!$A$5:$A$44,0))&"","") | G41: =IF(AND(E41="",F41=""),"",IF(E41=F41,"agree","DIFFER")) | I41: =IF(H41<>"",H41,IF(G41="agree",E41,""))
A42: L03 | B42: vague | C42: Use cases | E42: =IFERROR(INDEX('Annotator A'!$C$5:$C$44,MATCH($A42,'Annotator A'!$A$5:$A$44,0))&"","") | F42: =IFERROR(INDEX('Annotator B'!$C$5:$C$44,MATCH($A42,'Annotator B'!$A$5:$A$44,0))&"","") | G42: read both | I42: =IF(H42<>"",H42,"")
A43: L03 | B43: vague | C43: Value — Business impact | E43: =IFERROR(INDEX('Annotator A'!$D$5:$D$44,MATCH($A43,'Annotator A'!$A$5:$A$44,0))&"","") | F43: =IFERROR(INDEX('Annotator B'!$D$5:$D$44,MATCH($A43,'Annotator B'!$A$5:$A$44,0))&"","") | G43: =IF(AND(E43="",F43=""),"",IF(E43=F43,"agree","DIFFER")) | I43: =IF(H43<>"",H43,IF(G43="agree",E43,""))
A44: L03 | B44: vague | C44: Value — Productivity | E44: =IFERROR(INDEX('Annotator A'!$E$5:$E$44,MATCH($A44,'Annotator A'!$A$5:$A$44,0))&"","") | F44: =IFERROR(INDEX('Annotator B'!$E$5:$E$44,MATCH($A44,'Annotator B'!$A$5:$A$44,0))&"","") | G44: =IF(AND(E44="",F44=""),"",IF(E44=F44,"agree","DIFFER")) | I44: =IF(H44<>"",H44,IF(G44="agree",E44,""))
A45: L03 | B45: vague | C45: Value — Cost reduction | E45: =IFERROR(INDEX('Annotator A'!$F$5:$F$44,MATCH($A45,'Annotator A'!$A$5:$A$44,0))&"","") | F45: =IFERROR(INDEX('Annotator B'!$F$5:$F$44,MATCH($A45,'Annotator B'!$A$5:$A$44,0))&"","") | G45: =IF(AND(E45="",F45=""),"",IF(E45=F45,"agree","DIFFER")) | I45: =IF(H45<>"",H45,IF(G45="agree",E45,""))
A46: L03 | B46: vague | C46: Value — Revenue | E46: =IFERROR(INDEX('Annotator A'!$G$5:$G$44,MATCH($A46,'Annotator A'!$A$5:$A$44,0))&"","") | F46: =IFERROR(INDEX('Annotator B'!$G$5:$G$44,MATCH($A46,'Annotator B'!$A$5:$A$44,0))&"","") | G46: =IF(AND(E46="",F46=""),"",IF(E46=F46,"agree","DIFFER")) | I46: =IF(H46<>"",H46,IF(G46="agree",E46,""))
A47: L03 | B47: vague | C47: Value — Employee experience | E47: =IFERROR(INDEX('Annotator A'!$H$5:$H$44,MATCH($A47,'Annotator A'!$A$5:$A$44,0))&"","") | F47: =IFERROR(INDEX('Annotator B'!$H$5:$H$44,MATCH($A47,'Annotator B'!$A$5:$A$44,0))&"","") | G47: =IF(AND(E47="",F47=""),"",IF(E47=F47,"agree","DIFFER")) | I47: =IF(H47<>"",H47,IF(G47="agree",E47,""))
A48: L03 | B48: vague | C48: Value — Customer impact | E48: =IFERROR(INDEX('Annotator A'!$I$5:$I$44,MATCH($A48,'Annotator A'!$A$5:$A$44,0))&"","") | F48: =IFERROR(INDEX('Annotator B'!$I$5:$I$44,MATCH($A48,'Annotator B'!$A$5:$A$44,0))&"","") | G48: =IF(AND(E48="",F48=""),"",IF(E48=F48,"agree","DIFFER")) | I48: =IF(H48<>"",H48,IF(G48="agree",E48,""))
A49: L03 | B49: vague | C49: Value — Operational | E49: =IFERROR(INDEX('Annotator A'!$J$5:$J$44,MATCH($A49,'Annotator A'!$A$5:$A$44,0))&"","") | F49: =IFERROR(INDEX('Annotator B'!$J$5:$J$44,MATCH($A49,'Annotator B'!$A$5:$A$44,0))&"","") | G49: =IF(AND(E49="",F49=""),"",IF(E49=F49,"agree","DIFFER")) | I49: =IF(H49<>"",H49,IF(G49="agree",E49,""))
A50: L03 | B50: vague | C50: Value — Problem severity | E50: =IFERROR(INDEX('Annotator A'!$K$5:$K$44,MATCH($A50,'Annotator A'!$A$5:$A$44,0))&"","") | F50: =IFERROR(INDEX('Annotator B'!$K$5:$K$44,MATCH($A50,'Annotator B'!$A$5:$A$44,0))&"","") | G50: =IF(AND(E50="",F50=""),"",IF(E50=F50,"agree","DIFFER")) | I50: =IF(H50<>"",H50,IF(G50="agree",E50,""))
A51: L03 | B51: vague | C51: Value — Problem frequency | E51: =IFERROR(INDEX('Annotator A'!$L$5:$L$44,MATCH($A51,'Annotator A'!$A$5:$A$44,0))&"","") | F51: =IFERROR(INDEX('Annotator B'!$L$5:$L$44,MATCH($A51,'Annotator B'!$A$5:$A$44,0))&"","") | G51: =IF(AND(E51="",F51=""),"",IF(E51=F51,"agree","DIFFER")) | I51: =IF(H51<>"",H51,IF(G51="agree",E51,""))
A52: L03 | B52: vague | C52: Feasibility status | E52: =IFERROR(INDEX('Annotator A'!$M$5:$M$44,MATCH($A52,'Annotator A'!$A$5:$A$44,0))&"","") | F52: =IFERROR(INDEX('Annotator B'!$M$5:$M$44,MATCH($A52,'Annotator B'!$A$5:$A$44,0))&"","") | G52: =IF(AND(E52="",F52=""),"",IF(E52=F52,"agree","DIFFER")) | I52: =IF(H52<>"",H52,IF(G52="agree",E52,""))
A53: L03 | B53: vague | C53: Risk — Technical | E53: =IFERROR(INDEX('Annotator A'!$N$5:$N$44,MATCH($A53,'Annotator A'!$A$5:$A$44,0))&"","") | F53: =IFERROR(INDEX('Annotator B'!$N$5:$N$44,MATCH($A53,'Annotator B'!$A$5:$A$44,0))&"","") | G53: =IF(AND(E53="",F53=""),"",IF(E53=F53,"agree","DIFFER")) | I53: =IF(H53<>"",H53,IF(G53="agree",E53,""))
A54: L03 | B54: vague | C54: Risk — Security | E54: =IFERROR(INDEX('Annotator A'!$O$5:$O$44,MATCH($A54,'Annotator A'!$A$5:$A$44,0))&"","") | F54: =IFERROR(INDEX('Annotator B'!$O$5:$O$44,MATCH($A54,'Annotator B'!$A$5:$A$44,0))&"","") | G54: =IF(AND(E54="",F54=""),"",IF(E54=F54,"agree","DIFFER")) | I54: =IF(H54<>"",H54,IF(G54="agree",E54,""))
A55: L03 | B55: vague | C55: Risk — Privacy | E55: =IFERROR(INDEX('Annotator A'!$P$5:$P$44,MATCH($A55,'Annotator A'!$A$5:$A$44,0))&"","") | F55: =IFERROR(INDEX('Annotator B'!$P$5:$P$44,MATCH($A55,'Annotator B'!$A$5:$A$44,0))&"","") | G55: =IF(AND(E55="",F55=""),"",IF(E55=F55,"agree","DIFFER")) | I55: =IF(H55<>"",H55,IF(G55="agree",E55,""))
A56: L03 | B56: vague | C56: Risk — Compliance | E56: =IFERROR(INDEX('Annotator A'!$Q$5:$Q$44,MATCH($A56,'Annotator A'!$A$5:$A$44,0))&"","") | F56: =IFERROR(INDEX('Annotator B'!$Q$5:$Q$44,MATCH($A56,'Annotator B'!$A$5:$A$44,0))&"","") | G56: =IF(AND(E56="",F56=""),"",IF(E56=F56,"agree","DIFFER")) | I56: =IF(H56<>"",H56,IF(G56="agree",E56,""))
A57: L03 | B57: vague | C57: Risk — Financial | E57: =IFERROR(INDEX('Annotator A'!$R$5:$R$44,MATCH($A57,'Annotator A'!$A$5:$A$44,0))&"","") | F57: =IFERROR(INDEX('Annotator B'!$R$5:$R$44,MATCH($A57,'Annotator B'!$A$5:$A$44,0))&"","") | G57: =IF(AND(E57="",F57=""),"",IF(E57=F57,"agree","DIFFER")) | I57: =IF(H57<>"",H57,IF(G57="agree",E57,""))
A58: L03 | B58: vague | C58: Risk — Operational | E58: =IFERROR(INDEX('Annotator A'!$S$5:$S$44,MATCH($A58,'Annotator A'!$A$5:$A$44,0))&"","") | F58: =IFERROR(INDEX('Annotator B'!$S$5:$S$44,MATCH($A58,'Annotator B'!$A$5:$A$44,0))&"","") | G58: =IF(AND(E58="",F58=""),"",IF(E58=F58,"agree","DIFFER")) | I58: =IF(H58<>"",H58,IF(G58="agree",E58,""))
A59: L03 | B59: vague | C59: Risk — Adoption | E59: =IFERROR(INDEX('Annotator A'!$T$5:$T$44,MATCH($A59,'Annotator A'!$A$5:$A$44,0))&"","") | F59: =IFERROR(INDEX('Annotator B'!$T$5:$T$44,MATCH($A59,'Annotator B'!$A$5:$A$44,0))&"","") | G59: =IF(AND(E59="",F59=""),"",IF(E59=F59,"agree","DIFFER")) | I59: =IF(H59<>"",H59,IF(G59="agree",E59,""))
A60: L03 | B60: vague | C60: Risk — Data | E60: =IFERROR(INDEX('Annotator A'!$U$5:$U$44,MATCH($A60,'Annotator A'!$A$5:$A$44,0))&"","") | F60: =IFERROR(INDEX('Annotator B'!$U$5:$U$44,MATCH($A60,'Annotator B'!$A$5:$A$44,0))&"","") | G60: =IF(AND(E60="",F60=""),"",IF(E60=F60,"agree","DIFFER")) | I60: =IF(H60<>"",H60,IF(G60="agree",E60,""))
A61: L03 | B61: vague | C61: Risk — Vendor | E61: =IFERROR(INDEX('Annotator A'!$V$5:$V$44,MATCH($A61,'Annotator A'!$A$5:$A$44,0))&"","") | F61: =IFERROR(INDEX('Annotator B'!$V$5:$V$44,MATCH($A61,'Annotator B'!$A$5:$A$44,0))&"","") | G61: =IF(AND(E61="",F61=""),"",IF(E61=F61,"agree","DIFFER")) | I61: =IF(H61<>"",H61,IF(G61="agree",E61,""))
A62: L04 | B62: near-duplicate | C62: Use cases | D62: reorganise shared drive into consistent top-level folders | E62: =IFERROR(INDEX('Annotator A'!$C$5:$C$44,MATCH($A62,'Annotator A'!$A$5:$A$44,0))&"","") | F62: =IFERROR(INDEX('Annotator B'!$C$5:$C$44,MATCH($A62,'Annotator B'!$A$5:$A$44,0))&"","") | G62: read both | I62: =IF(H62<>"",H62,"")
A63: L04 | B63: near-duplicate | C63: Value — Business impact | E63: =IFERROR(INDEX('Annotator A'!$D$5:$D$44,MATCH($A63,'Annotator A'!$A$5:$A$44,0))&"","") | F63: =IFERROR(INDEX('Annotator B'!$D$5:$D$44,MATCH($A63,'Annotator B'!$A$5:$A$44,0))&"","") | G63: =IF(AND(E63="",F63=""),"",IF(E63=F63,"agree","DIFFER")) | I63: =IF(H63<>"",H63,IF(G63="agree",E63,""))
A64: L04 | B64: near-duplicate | C64: Value — Productivity | D64: Low | E64: =IFERROR(INDEX('Annotator A'!$E$5:$E$44,MATCH($A64,'Annotator A'!$A$5:$A$44,0))&"","") | F64: =IFERROR(INDEX('Annotator B'!$E$5:$E$44,MATCH($A64,'Annotator B'!$A$5:$A$44,0))&"","") | G64: =IF(AND(E64="",F64=""),"",IF(E64=F64,"agree","DIFFER")) | I64: =IF(H64<>"",H64,IF(G64="agree",E64,""))
A65: L04 | B65: near-duplicate | C65: Value — Cost reduction | E65: =IFERROR(INDEX('Annotator A'!$F$5:$F$44,MATCH($A65,'Annotator A'!$A$5:$A$44,0))&"","") | F65: =IFERROR(INDEX('Annotator B'!$F$5:$F$44,MATCH($A65,'Annotator B'!$A$5:$A$44,0))&"","") | G65: =IF(AND(E65="",F65=""),"",IF(E65=F65,"agree","DIFFER")) | I65: =IF(H65<>"",H65,IF(G65="agree",E65,""))
A66: L04 | B66: near-duplicate | C66: Value — Revenue | E66: =IFERROR(INDEX('Annotator A'!$G$5:$G$44,MATCH($A66,'Annotator A'!$A$5:$A$44,0))&"","") | F66: =IFERROR(INDEX('Annotator B'!$G$5:$G$44,MATCH($A66,'Annotator B'!$A$5:$A$44,0))&"","") | G66: =IF(AND(E66="",F66=""),"",IF(E66=F66,"agree","DIFFER")) | I66: =IF(H66<>"",H66,IF(G66="agree",E66,""))
A67: L04 | B67: near-duplicate | C67: Value — Employee experience | E67: =IFERROR(INDEX('Annotator A'!$H$5:$H$44,MATCH($A67,'Annotator A'!$A$5:$A$44,0))&"","") | F67: =IFERROR(INDEX('Annotator B'!$H$5:$H$44,MATCH($A67,'Annotator B'!$A$5:$A$44,0))&"","") | G67: =IF(AND(E67="",F67=""),"",IF(E67=F67,"agree","DIFFER")) | I67: =IF(H67<>"",H67,IF(G67="agree",E67,""))
A68: L04 | B68: near-duplicate | C68: Value — Customer impact | E68: =IFERROR(INDEX('Annotator A'!$I$5:$I$44,MATCH($A68,'Annotator A'!$A$5:$A$44,0))&"","") | F68: =IFERROR(INDEX('Annotator B'!$I$5:$I$44,MATCH($A68,'Annotator B'!$A$5:$A$44,0))&"","") | G68: =IF(AND(E68="",F68=""),"",IF(E68=F68,"agree","DIFFER")) | I68: =IF(H68<>"",H68,IF(G68="agree",E68,""))
A69: L04 | B69: near-duplicate | C69: Value — Operational | E69: =IFERROR(INDEX('Annotator A'!$J$5:$J$44,MATCH($A69,'Annotator A'!$A$5:$A$44,0))&"","") | F69: =IFERROR(INDEX('Annotator B'!$J$5:$J$44,MATCH($A69,'Annotator B'!$A$5:$A$44,0))&"","") | G69: =IF(AND(E69="",F69=""),"",IF(E69=F69,"agree","DIFFER")) | I69: =IF(H69<>"",H69,IF(G69="agree",E69,""))
A70: L04 | B70: near-duplicate | C70: Value — Problem severity | E70: =IFERROR(INDEX('Annotator A'!$K$5:$K$44,MATCH($A70,'Annotator A'!$A$5:$A$44,0))&"","") | F70: =IFERROR(INDEX('Annotator B'!$K$5:$K$44,MATCH($A70,'Annotator B'!$A$5:$A$44,0))&"","") | G70: =IF(AND(E70="",F70=""),"",IF(E70=F70,"agree","DIFFER")) | I70: =IF(H70<>"",H70,IF(G70="agree",E70,""))
A71: L04 | B71: near-duplicate | C71: Value — Problem frequency | D71: Moderate | E71: =IFERROR(INDEX('Annotator A'!$L$5:$L$44,MATCH($A71,'Annotator A'!$A$5:$A$44,0))&"","") | F71: =IFERROR(INDEX('Annotator B'!$L$5:$L$44,MATCH($A71,'Annotator B'!$A$5:$A$44,0))&"","") | G71: =IF(AND(E71="",F71=""),"",IF(E71=F71,"agree","DIFFER")) | I71: =IF(H71<>"",H71,IF(G71="agree",E71,""))
A72: L04 | B72: near-duplicate | C72: Feasibility status | D72: HIGHLY_FEASIBLE | E72: =IFERROR(INDEX('Annotator A'!$M$5:$M$44,MATCH($A72,'Annotator A'!$A$5:$A$44,0))&"","") | F72: =IFERROR(INDEX('Annotator B'!$M$5:$M$44,MATCH($A72,'Annotator B'!$A$5:$A$44,0))&"","") | G72: =IF(AND(E72="",F72=""),"",IF(E72=F72,"agree","DIFFER")) | I72: =IF(H72<>"",H72,IF(G72="agree",E72,""))
A73: L04 | B73: near-duplicate | C73: Risk — Technical | E73: =IFERROR(INDEX('Annotator A'!$N$5:$N$44,MATCH($A73,'Annotator A'!$A$5:$A$44,0))&"","") | F73: =IFERROR(INDEX('Annotator B'!$N$5:$N$44,MATCH($A73,'Annotator B'!$A$5:$A$44,0))&"","") | G73: =IF(AND(E73="",F73=""),"",IF(E73=F73,"agree","DIFFER")) | I73: =IF(H73<>"",H73,IF(G73="agree",E73,""))
A74: L04 | B74: near-duplicate | C74: Risk — Security | E74: =IFERROR(INDEX('Annotator A'!$O$5:$O$44,MATCH($A74,'Annotator A'!$A$5:$A$44,0))&"","") | F74: =IFERROR(INDEX('Annotator B'!$O$5:$O$44,MATCH($A74,'Annotator B'!$A$5:$A$44,0))&"","") | G74: =IF(AND(E74="",F74=""),"",IF(E74=F74,"agree","DIFFER")) | I74: =IF(H74<>"",H74,IF(G74="agree",E74,""))
A75: L04 | B75: near-duplicate | C75: Risk — Privacy | E75: =IFERROR(INDEX('Annotator A'!$P$5:$P$44,MATCH($A75,'Annotator A'!$A$5:$A$44,0))&"","") | F75: =IFERROR(INDEX('Annotator B'!$P$5:$P$44,MATCH($A75,'Annotator B'!$A$5:$A$44,0))&"","") | G75: =IF(AND(E75="",F75=""),"",IF(E75=F75,"agree","DIFFER")) | I75: =IF(H75<>"",H75,IF(G75="agree",E75,""))
A76: L04 | B76: near-duplicate | C76: Risk — Compliance | E76: =IFERROR(INDEX('Annotator A'!$Q$5:$Q$44,MATCH($A76,'Annotator A'!$A$5:$A$44,0))&"","") | F76: =IFERROR(INDEX('Annotator B'!$Q$5:$Q$44,MATCH($A76,'Annotator B'!$A$5:$A$44,0))&"","") | G76: =IF(AND(E76="",F76=""),"",IF(E76=F76,"agree","DIFFER")) | I76: =IF(H76<>"",H76,IF(G76="agree",E76,""))
A77: L04 | B77: near-duplicate | C77: Risk — Financial | E77: =IFERROR(INDEX('Annotator A'!$R$5:$R$44,MATCH($A77,'Annotator A'!$A$5:$A$44,0))&"","") | F77: =IFERROR(INDEX('Annotator B'!$R$5:$R$44,MATCH($A77,'Annotator B'!$A$5:$A$44,0))&"","") | G77: =IF(AND(E77="",F77=""),"",IF(E77=F77,"agree","DIFFER")) | I77: =IF(H77<>"",H77,IF(G77="agree",E77,""))
A78: L04 | B78: near-duplicate | C78: Risk — Operational | E78: =IFERROR(INDEX('Annotator A'!$S$5:$S$44,MATCH($A78,'Annotator A'!$A$5:$A$44,0))&"","") | F78: =IFERROR(INDEX('Annotator B'!$S$5:$S$44,MATCH($A78,'Annotator B'!$A$5:$A$44,0))&"","") | G78: =IF(AND(E78="",F78=""),"",IF(E78=F78,"agree","DIFFER")) | I78: =IF(H78<>"",H78,IF(G78="agree",E78,""))
A79: L04 | B79: near-duplicate | C79: Risk — Adoption | E79: =IFERROR(INDEX('Annotator A'!$T$5:$T$44,MATCH($A79,'Annotator A'!$A$5:$A$44,0))&"","") | F79: =IFERROR(INDEX('Annotator B'!$T$5:$T$44,MATCH($A79,'Annotator B'!$A$5:$A$44,0))&"","") | G79: =IF(AND(E79="",F79=""),"",IF(E79=F79,"agree","DIFFER")) | I79: =IF(H79<>"",H79,IF(G79="agree",E79,""))
A80: L04 | B80: near-duplicate | C80: Risk — Data | E80: =IFERROR(INDEX('Annotator A'!$U$5:$U$44,MATCH($A80,'Annotator A'!$A$5:$A$44,0))&"","") | F80: =IFERROR(INDEX('Annotator B'!$U$5:$U$44,MATCH($A80,'Annotator B'!$A$5:$A$44,0))&"","") | G80: =IF(AND(E80="",F80=""),"",IF(E80=F80,"agree","DIFFER")) | I80: =IF(H80<>"",H80,IF(G80="agree",E80,""))
A81: L04 | B81: near-duplicate | C81: Risk — Vendor | E81: =IFERROR(INDEX('Annotator A'!$V$5:$V$44,MATCH($A81,'Annotator A'!$A$5:$A$44,0))&"","") | F81: =IFERROR(INDEX('Annotator B'!$V$5:$V$44,MATCH($A81,'Annotator B'!$A$5:$A$44,0))&"","") | G81: =IF(AND(E81="",F81=""),"",IF(E81=F81,"agree","DIFFER")) | I81: =IF(H81<>"",H81,IF(G81="agree",E81,""))
A82: L05 | B82: vague | C82: Use cases | E82: =IFERROR(INDEX('Annotator A'!$C$5:$C$44,MATCH($A82,'Annotator A'!$A$5:$A$44,0))&"","") | F82: =IFERROR(INDEX('Annotator B'!$C$5:$C$44,MATCH($A82,'Annotator B'!$A$5:$A$44,0))&"","") | G82: read both | I82: =IF(H82<>"",H82,"")
A83: L05 | B83: vague | C83: Value — Business impact | E83: =IFERROR(INDEX('Annotator A'!$D$5:$D$44,MATCH($A83,'Annotator A'!$A$5:$A$44,0))&"","") | F83: =IFERROR(INDEX('Annotator B'!$D$5:$D$44,MATCH($A83,'Annotator B'!$A$5:$A$44,0))&"","") | G83: =IF(AND(E83="",F83=""),"",IF(E83=F83,"agree","DIFFER")) | I83: =IF(H83<>"",H83,IF(G83="agree",E83,""))
A84: L05 | B84: vague | C84: Value — Productivity | E84: =IFERROR(INDEX('Annotator A'!$E$5:$E$44,MATCH($A84,'Annotator A'!$A$5:$A$44,0))&"","") | F84: =IFERROR(INDEX('Annotator B'!$E$5:$E$44,MATCH($A84,'Annotator B'!$A$5:$A$44,0))&"","") | G84: =IF(AND(E84="",F84=""),"",IF(E84=F84,"agree","DIFFER")) | I84: =IF(H84<>"",H84,IF(G84="agree",E84,""))
A85: L05 | B85: vague | C85: Value — Cost reduction | E85: =IFERROR(INDEX('Annotator A'!$F$5:$F$44,MATCH($A85,'Annotator A'!$A$5:$A$44,0))&"","") | F85: =IFERROR(INDEX('Annotator B'!$F$5:$F$44,MATCH($A85,'Annotator B'!$A$5:$A$44,0))&"","") | G85: =IF(AND(E85="",F85=""),"",IF(E85=F85,"agree","DIFFER")) | I85: =IF(H85<>"",H85,IF(G85="agree",E85,""))
A86: L05 | B86: vague | C86: Value — Revenue | E86: =IFERROR(INDEX('Annotator A'!$G$5:$G$44,MATCH($A86,'Annotator A'!$A$5:$A$44,0))&"","") | F86: =IFERROR(INDEX('Annotator B'!$G$5:$G$44,MATCH($A86,'Annotator B'!$A$5:$A$44,0))&"","") | G86: =IF(AND(E86="",F86=""),"",IF(E86=F86,"agree","DIFFER")) | I86: =IF(H86<>"",H86,IF(G86="agree",E86,""))
A87: L05 | B87: vague | C87: Value — Employee experience | E87: =IFERROR(INDEX('Annotator A'!$H$5:$H$44,MATCH($A87,'Annotator A'!$A$5:$A$44,0))&"","") | F87: =IFERROR(INDEX('Annotator B'!$H$5:$H$44,MATCH($A87,'Annotator B'!$A$5:$A$44,0))&"","") | G87: =IF(AND(E87="",F87=""),"",IF(E87=F87,"agree","DIFFER")) | I87: =IF(H87<>"",H87,IF(G87="agree",E87,""))
A88: L05 | B88: vague | C88: Value — Customer impact | E88: =IFERROR(INDEX('Annotator A'!$I$5:$I$44,MATCH($A88,'Annotator A'!$A$5:$A$44,0))&"","") | F88: =IFERROR(INDEX('Annotator B'!$I$5:$I$44,MATCH($A88,'Annotator B'!$A$5:$A$44,0))&"","") | G88: =IF(AND(E88="",F88=""),"",IF(E88=F88,"agree","DIFFER")) | I88: =IF(H88<>"",H88,IF(G88="agree",E88,""))
A89: L05 | B89: vague | C89: Value — Operational | E89: =IFERROR(INDEX('Annotator A'!$J$5:$J$44,MATCH($A89,'Annotator A'!$A$5:$A$44,0))&"","") | F89: =IFERROR(INDEX('Annotator B'!$J$5:$J$44,MATCH($A89,'Annotator B'!$A$5:$A$44,0))&"","") | G89: =IF(AND(E89="",F89=""),"",IF(E89=F89,"agree","DIFFER")) | I89: =IF(H89<>"",H89,IF(G89="agree",E89,""))
A90: L05 | B90: vague | C90: Value — Problem severity | E90: =IFERROR(INDEX('Annotator A'!$K$5:$K$44,MATCH($A90,'Annotator A'!$A$5:$A$44,0))&"","") | F90: =IFERROR(INDEX('Annotator B'!$K$5:$K$44,MATCH($A90,'Annotator B'!$A$5:$A$44,0))&"","") | G90: =IF(AND(E90="",F90=""),"",IF(E90=F90,"agree","DIFFER")) | I90: =IF(H90<>"",H90,IF(G90="agree",E90,""))
A91: L05 | B91: vague | C91: Value — Problem frequency | E91: =IFERROR(INDEX('Annotator A'!$L$5:$L$44,MATCH($A91,'Annotator A'!$A$5:$A$44,0))&"","") | F91: =IFERROR(INDEX('Annotator B'!$L$5:$L$44,MATCH($A91,'Annotator B'!$A$5:$A$44,0))&"","") | G91: =IF(AND(E91="",F91=""),"",IF(E91=F91,"agree","DIFFER")) | I91: =IF(H91<>"",H91,IF(G91="agree",E91,""))
A92: L05 | B92: vague | C92: Feasibility status | E92: =IFERROR(INDEX('Annotator A'!$M$5:$M$44,MATCH($A92,'Annotator A'!$A$5:$A$44,0))&"","") | F92: =IFERROR(INDEX('Annotator B'!$M$5:$M$44,MATCH($A92,'Annotator B'!$A$5:$A$44,0))&"","") | G92: =IF(AND(E92="",F92=""),"",IF(E92=F92,"agree","DIFFER")) | I92: =IF(H92<>"",H92,IF(G92="agree",E92,""))
A93: L05 | B93: vague | C93: Risk — Technical | E93: =IFERROR(INDEX('Annotator A'!$N$5:$N$44,MATCH($A93,'Annotator A'!$A$5:$A$44,0))&"","") | F93: =IFERROR(INDEX('Annotator B'!$N$5:$N$44,MATCH($A93,'Annotator B'!$A$5:$A$44,0))&"","") | G93: =IF(AND(E93="",F93=""),"",IF(E93=F93,"agree","DIFFER")) | I93: =IF(H93<>"",H93,IF(G93="agree",E93,""))
A94: L05 | B94: vague | C94: Risk — Security | E94: =IFERROR(INDEX('Annotator A'!$O$5:$O$44,MATCH($A94,'Annotator A'!$A$5:$A$44,0))&"","") | F94: =IFERROR(INDEX('Annotator B'!$O$5:$O$44,MATCH($A94,'Annotator B'!$A$5:$A$44,0))&"","") | G94: =IF(AND(E94="",F94=""),"",IF(E94=F94,"agree","DIFFER")) | I94: =IF(H94<>"",H94,IF(G94="agree",E94,""))
A95: L05 | B95: vague | C95: Risk — Privacy | E95: =IFERROR(INDEX('Annotator A'!$P$5:$P$44,MATCH($A95,'Annotator A'!$A$5:$A$44,0))&"","") | F95: =IFERROR(INDEX('Annotator B'!$P$5:$P$44,MATCH($A95,'Annotator B'!$A$5:$A$44,0))&"","") | G95: =IF(AND(E95="",F95=""),"",IF(E95=F95,"agree","DIFFER")) | I95: =IF(H95<>"",H95,IF(G95="agree",E95,""))
A96: L05 | B96: vague | C96: Risk — Compliance | E96: =IFERROR(INDEX('Annotator A'!$Q$5:$Q$44,MATCH($A96,'Annotator A'!$A$5:$A$44,0))&"","") | F96: =IFERROR(INDEX('Annotator B'!$Q$5:$Q$44,MATCH($A96,'Annotator B'!$A$5:$A$44,0))&"","") | G96: =IF(AND(E96="",F96=""),"",IF(E96=F96,"agree","DIFFER")) | I96: =IF(H96<>"",H96,IF(G96="agree",E96,""))
A97: L05 | B97: vague | C97: Risk — Financial | E97: =IFERROR(INDEX('Annotator A'!$R$5:$R$44,MATCH($A97,'Annotator A'!$A$5:$A$44,0))&"","") | F97: =IFERROR(INDEX('Annotator B'!$R$5:$R$44,MATCH($A97,'Annotator B'!$A$5:$A$44,0))&"","") | G97: =IF(AND(E97="",F97=""),"",IF(E97=F97,"agree","DIFFER")) | I97: =IF(H97<>"",H97,IF(G97="agree",E97,""))
A98: L05 | B98: vague | C98: Risk — Operational | E98: =IFERROR(INDEX('Annotator A'!$S$5:$S$44,MATCH($A98,'Annotator A'!$A$5:$A$44,0))&"","") | F98: =IFERROR(INDEX('Annotator B'!$S$5:$S$44,MATCH($A98,'Annotator B'!$A$5:$A$44,0))&"","") | G98: =IF(AND(E98="",F98=""),"",IF(E98=F98,"agree","DIFFER")) | I98: =IF(H98<>"",H98,IF(G98="agree",E98,""))
A99: L05 | B99: vague | C99: Risk — Adoption | E99: =IFERROR(INDEX('Annotator A'!$T$5:$T$44,MATCH($A99,'Annotator A'!$A$5:$A$44,0))&"","") | F99: =IFERROR(INDEX('Annotator B'!$T$5:$T$44,MATCH($A99,'Annotator B'!$A$5:$A$44,0))&"","") | G99: =IF(AND(E99="",F99=""),"",IF(E99=F99,"agree","DIFFER")) | I99: =IF(H99<>"",H99,IF(G99="agree",E99,""))
A100: L05 | B100: vague | C100: Risk — Data | E100: =IFERROR(INDEX('Annotator A'!$U$5:$U$44,MATCH($A100,'Annotator A'!$A$5:$A$44,0))&"","") | F100: =IFERROR(INDEX('Annotator B'!$U$5:$U$44,MATCH($A100,'Annotator B'!$A$5:$A$44,0))&"","") | G100: =IF(AND(E100="",F100=""),"",IF(E100=F100,"agree","DIFFER")) | I100: =IF(H100<>"",H100,IF(G100="agree",E100,""))
...

Sheet Lists
A1: Band | B1: Feasibility | C1: Risk present
A2: Negligible | B2: HIGHLY_FEASIBLE | C2: Yes
A3: Low | B3: FEASIBLE_WITH_CONDITIONS
A4: Moderate | B4: REQUIRES_INVESTIGATION
A5: High | B5: NOT_CURRENTLY_FEASIBLE
A6: Very high

Sheet Annotator A
A1: Annotator name: | D1: Ideas with a feasibility status entered: | H1: =COUNTA(M5:M44)&" of 40"
A2: Yellow cells are yours to fill in. Leave any cell blank if you cannot judge it from the text — blank is not wrong.
A4: ID | B4: Idea title (for reference) | C4: Use cases — one per line | D4: Value — Business impact | E4: Value — Productivity | F4: Value — Cost reduction | G4: Value — Revenue | H4: Value — Employee experience | I4: Value — Customer impact | J4: Value — Operational | K4: Value — Problem severity | L4: Value — Problem frequency | M4: Feasibility status | N4: Risk — Technical | O4: Risk — Security | P4: Risk — Privacy | Q4: Risk — Compliance | R4: Risk — Financial | S4: Risk — Operational | T4: Risk — Adoption | U4: Risk — Data | V4: Risk — Vendor | W4: Notes / doubts (optional)
A5: L01 | B5: No one can see where an approval is stuck
A6: L02 | B6: Auto-approve any expense report without manager review
A7: L03 | B7: Speed up approvals
A8: L04 | B8: Fix our messy file storage
A9: L05 | B9: Better reporting
A10: L06 | B10: Improve data quality
A11: L07 | B11: Facial-recognition-based attendance tracking
A12: L08 | B12: New starters wait too long for a laptop
A13: L09 | B13: Faster laptop provisioning for new hires
A14: L10 | B14: Clean up the shared drive folder structure
A15: L11 | B15: Self-service password reset portal
A16: L12 | B16: Fewer meetings
... A44: L40 | B44: Automated expense approval reminders

Sheet Annotator B
A1: Annotator name: | D1: Ideas with a feasibility status entered: | H1: =COUNTA(M5:M44)&" of 40"
A2: Yellow cells are yours to fill in. Leave any cell blank if you cannot judge it from the text — blank is not wrong.
A4: ID | B4: Idea title (for reference) | C4: Use cases — one per line | D4: Value — Business impact | E4: Value — Productivity | F4: Value — Cost reduction | G4: Value — Revenue | H4: Value — Employee experience | I4: Value — Customer impact | J4: Value — Operational | K4: Value — Problem severity | L4: Value — Problem frequency | M4: Feasibility status | N4: Risk — Technical | O4: Risk — Security | P4: Risk — Privacy | Q4: Risk — Compliance | R4: Risk — Financial | S4: Risk — Operational | T4: Risk — Adoption | U4: Risk — Data | V4: Risk — Vendor | W4: Notes / doubts (optional)
A5: L01 | B5: No one can see where an approval is stuck
A6: L02 | B6: Auto-approve any expense report without manager review
A7: L03 | B7: Speed up approvals
A8: L04 | B8: Fix our messy file storage
A9: L05 | B9: Better reporting
A10: L06 | B10: Improve data quality
A11: L07 | B11: Facial-recognition-based attendance tracking
A12: L08 | B12: New starters wait too long for a laptop
A13: L09 | B13: Faster laptop provisioning for new hires
A14: L10 | B14: Clean up the shared drive folder structure
A15: L11 | B15: Self-service password reset portal
A16: L12 | B16: Fewer meetings
... A44: L40 | B44: Automated expense approval reminders

Sheet Key
A1: ID | B1: Case name in tests/evals/cases.ts | C1: SPEC group | D1: Title
A2: L01 | B2: near-duplicate (2 of 2) — no one can see where an approval is stuck | C2: near-duplicate | D2: No one can see where an approval is stuck
A3: L02 | B3: infeasible — auto-approving expenses with no review, against financial controls | C3: infeasible | D3: Auto-approve any expense report without manager review
A4: L03 | B4: vague — speed up approvals, unspecified | C4: vague | D4: Speed up approvals
A5: L04 | B5: near-duplicate (2 of 2) — same problem, phrased independently | C5: near-duplicate | D5: Fix our messy file storage
A6: L05 | B6: vague — better reporting, no specifics | C6: vague | D6: Better reporting
A7: L06 | B7: vague — improve data quality, unspecified | C7: vague | D7: Improve data quality
A8: L07 | B8: infeasible — biometric attendance tracking against a stated policy constraint | C8: infeasible | D8: Facial-recognition-based attendance tracking
A9: L08 | B9: near-duplicate (2 of 2) — new starters wait too long for a laptop | C9: near-duplicate | D9: New starters wait too long for a laptop
A10: L09 | B10: near-duplicate (1 of 2) — faster laptop provisioning for new hires | C10: near-duplicate | D10: Faster laptop provisioning for new hires
A11: L10 | B11: near-duplicate (1 of 2) — shared drive folder cleanup | C11: near-duplicate | D11: Clean up the shared drive folder structure
A12: L11 | B12: well-specified — self-service password reset | C12: strong | D12: Self-service password reset portal
... A41: L40 | B41: well-specified — expense approval automation | C41: strong | D41: Automated expense approval reminders
